tobit_reg/__init__.py
tobit_reg/tobit_reg.py
tobit_reg-0.0.1.dist-info/METADATA
tobit_reg-0.0.1.dist-info/WHEEL
tobit_reg-0.0.1.dist-info/licenses/LICENSE
tobit_reg-0.0.1.dist-info/RECORD
